pdkmaster/io/coriolis/__init__.py
pdkmaster/io/coriolis/doit.py
pdkmaster/io/coriolis/export.py
pdkmaster_io_coriolis-0.1.0.post1.dist-info/METADATA
pdkmaster_io_coriolis-0.1.0.post1.dist-info/WHEEL
pdkmaster_io_coriolis-0.1.0.post1.dist-info/entry_points.txt
pdkmaster_io_coriolis-0.1.0.post1.dist-info/licenses/LICENSE.md
pdkmaster_io_coriolis-0.1.0.post1.dist-info/RECORD
